env2cli/__init__.py
env2cli-0.0.1.dist-info/METADATA
env2cli-0.0.1.dist-info/WHEEL
env2cli-0.0.1.dist-info/top_level.txt
env2cli-0.0.1.dist-info/RECORD
