Metadata-Version: 2.1
Name: env2cli
Version: 0.0.1
Summary: Converts environment variables into cli arguments for easy maintainable docker entry point
Home-page: https://github.com/AvivAbramovich/Env2Cli
Author: Aviv Abramovich
Author-email: AvivAbramovich@gmail.com
License: UNKNOWN
Project-URL: Bug Tracker, https://github.com/AvivAbramovich/Env2Cli/issues
Platform: UNKNOWN
Classifier: Programming Language :: Python :: 3
Classifier: Operating System :: OS Independent
